setup.py
stat_distributions_prob/Binomialdistribution.py
stat_distributions_prob/Gaussiandistribution.py
stat_distributions_prob/Generaldistribution.py
stat_distributions_prob/__init__.py
stat_distributions_prob.egg-info/PKG-INFO
stat_distributions_prob.egg-info/SOURCES.txt
stat_distributions_prob.egg-info/dependency_links.txt
stat_distributions_prob.egg-info/not-zip-safe
stat_distributions_prob.egg-info/top_level.txt