Metadata-Version: 1.0
Name: stat-distributions-prob
Version: 0.1
Summary: Gaussian and Binomial distributions
Home-page: UNKNOWN
Author: Philip Wong
Author-email: UNKNOWN
License: UNKNOWN
Platform: UNKNOWN
